setup.py
GradeCurve/Gaussiandistribution.py
GradeCurve/Generaldistribution.py
GradeCurve/GradeCurve.py
GradeCurve/__init__.py
GradeCurve.egg-info/PKG-INFO
GradeCurve.egg-info/SOURCES.txt
GradeCurve.egg-info/dependency_links.txt
GradeCurve.egg-info/not-zip-safe
GradeCurve.egg-info/top_level.txt