Metadata-Version: 1.0
Name: GradeCurve
Version: 1.0.5
Summary: Curve grades on a test
Home-page: UNKNOWN
Author: Celestin Hermez
Author-email: celestinhermez@gmail.com
License: UNKNOWN
Platform: UNKNOWN
